segmenttree
