Metadata-Version: 1.0
Name: segmenttree
Version: 0.0.7
Summary: A Python implementation of Segment Tree
Home-page: http://liangsun.org/posts/a-python-implementation-of-segment-tree/
Author: Liang Sun
Author-email: i@liangsun.org
License: MIT License
Keywords: segment,tree
Platform: any
